CHANGELOG.md
LICENSE
README.md
SECURITY.md
ihatemoney/__init__.py
ihatemoney/babel.cfg
ihatemoney/babel_utils.py
ihatemoney/currency_convertor.py
ihatemoney/default_settings.py
ihatemoney/emails.py
ihatemoney/forms.py
ihatemoney/history.py
ihatemoney/manage.py
ihatemoney/messages.pot
ihatemoney/models.py
ihatemoney/monkeypath_continuum.py
ihatemoney/run.py
ihatemoney/utils.py
ihatemoney/versioning.py
ihatemoney/web.py
ihatemoney/wsgi.py
ihatemoney/api/__init__.py
ihatemoney/api/common.py
ihatemoney/api/v1/__init__.py
ihatemoney/api/v1/resources.py
ihatemoney/conf-templates/apache-vhost.conf.j2
ihatemoney/conf-templates/gunicorn.conf.py.j2
ihatemoney/conf-templates/ihatemoney.cfg.j2
ihatemoney/conf-templates/nginx.conf.j2
ihatemoney/conf-templates/supervisord.conf.j2
ihatemoney/migrations/README
ihatemoney/migrations/alembic.ini
ihatemoney/migrations/env.py
ihatemoney/migrations/script.py.mako
ihatemoney/migrations/versions/26d6a218c329_.py
ihatemoney/migrations/versions/2dcb0c0048dc_autologger.py
ihatemoney/migrations/versions/6c6fb2b7f229_.py
ihatemoney/migrations/versions/7a9b38559992_new_bill_type_attribute_added.py
ihatemoney/migrations/versions/927ed575acbd_add_currencies.py
ihatemoney/migrations/versions/a67119aa3ee5_migrate_negative_weights.py
ihatemoney/migrations/versions/afbf27e6ef20_add_bill_import_date_field.py
ihatemoney/migrations/versions/b78f8a8bdb16_hash_project_passwords.py
ihatemoney/migrations/versions/b9a10d5d63ce_.py
ihatemoney/migrations/versions/cb038f79982e_sqlite_autoincrement.py
ihatemoney/migrations/versions/f629c8ef4ab0_initialize_all_members_weights_to_1.py
ihatemoney/static/favicon.ico
ihatemoney/static/css/bootstrap.min.css
ihatemoney/static/css/datatables.min.css
ihatemoney/static/css/download_mobile_app.css
ihatemoney/static/css/main.css
ihatemoney/static/css/tagsinput.css
ihatemoney/static/fonts/OFL.txt
ihatemoney/static/fonts/comfortaa-regular-webfont.eot
ihatemoney/static/fonts/comfortaa-regular-webfont.svg
ihatemoney-7.0.0.dist-info/METADATA
ihatemoney-7.0.0.dist-info/WHEEL
ihatemoney-7.0.0.dist-info/entry_points.txt
ihatemoney-7.0.0.dist-info/licenses/LICENSE
ihatemoney-7.0.0.dist-info/RECORD
