Metadata-Version: 2.1
Name: ihatemoney
Version: 7.0.0
Summary: A simple shared budget manager web application.
Project-URL: Source Code, https://github.com/spiral-project/ihatemoney
Project-URL: Main instance, https://ihatemoney.org/
Project-URL: Mobile app, https://ihatemoney.org/mobile
Project-URL: Documentation, https://ihatemoney.readthedocs.io/en/latest/
Author-email: Alexis Métaireau & contributors <alexis@notmyidea.org>
License: Copyright (c) 2011 by Alexis Métaireau and contributors.  See AUTHORS
License-File: LICENSE
Keywords: budget,web
Classifier: Programming Language :: Python
Classifier: Programming Language :: Python :: 3
Classifier: Programming Language :: Python :: 3.11
Classifier: Programming Language :: Python :: 3.12
Classifier: Programming Language :: Python :: 3.13
Classifier: Topic :: Internet :: WWW/HTTP
Classifier: Topic :: Internet :: WWW/HTTP :: WSGI :: Application
Requires-Python: >=3.11
Requires-Dist: cachetools~=6.2.4
Requires-Dist: debts~=0.5
Requires-Dist: email-validator~=2.3.0
Requires-Dist: flask-babel~=4.0.0
Requires-Dist: flask-cors~=6.0.2
Requires-Dist: flask-limiter~=4.1.1
Requires-Dist: flask-mail~=0.10.0
Requires-Dist: flask-migrate~=4.1.0
Requires-Dist: flask-restful~=0.3.10
Requires-Dist: flask-sqlalchemy~=3.1.1
Requires-Dist: flask-talisman~=1.1.0
Requires-Dist: flask-wtf~=1.2.2
Requires-Dist: flask~=3.1.2
Requires-Dist: itsdangerous~=2.2.0
Requires-Dist: jinja2~=3.1.6
Requires-Dist: python-dateutil
Requires-Dist: qrcode~=8.2
Requires-Dist: requests~=2.32.5
Requires-Dist: sqlalchemy-continuum~=1.5.2
Requires-Dist: sqlalchemy~=2.0.45
Requires-Dist: werkzeug~=3.1.5
Requires-Dist: wtforms~=3.2.1
Provides-Extra: database
Requires-Dist: psycopg2-binary~=2.9.11; extra == 'database'
Requires-Dist: pymysql~=1.1.2; extra == 'database'
Provides-Extra: dev
Requires-Dist: isort~=7.0.0; extra == 'dev'
Requires-Dist: pytest-flask~=1.3.0; extra == 'dev'
Requires-Dist: pytest~=9.0.2; extra == 'dev'
Requires-Dist: ruff~=0.14.13; extra == 'dev'
Requires-Dist: vermin~=1.8.0; extra == 'dev'
Requires-Dist: zest-releaser~=9.8.0; extra == 'dev'
Provides-Extra: doc
Requires-Dist: docutils~=0.22.4; extra == 'doc'
Requires-Dist: myst-parser~=5.0.0; extra == 'doc'
Requires-Dist: sphinx~=9.0.4; extra == 'doc'
